{
  "run_name": "final_gru_notime_seed43_e10",
  "model_type": "gru_notime",
  "train_loss_mode": "observed_context",
  "num_parameters": 7645,
  "config": {
    "solver_type": "dopri5",
    "atol": 0.001,
    "rtol": 0.001,
    "in_features": 1,
    "hidden_dim": 32,
    "ode_hidden_dim": null,
    "gru_time_hidden_dim": null,
    "gru_notime_hidden_dim": 42,
    "input_dim": 1,
    "output_dim": 1,
    "signal_type": "sine",
    "is_time_series": true,
    "model_type": "gru_notime",
    "batch_size": 64,
    "lr": 0.001,
    "epochs": 10,
    "seed": 43,
    "train_loss_mode": "observed_context",
    "context_start": 0.0,
    "context_end": 5.0,
    "future_end": 10.0,
    "n_context_points": 50,
    "n_future_points": 50,
    "min_observed_context_points": 2,
    "observation_prob": 0.8,
    "noise_std": 0.01,
    "train_size": 500,
    "val_size": 100,
    "test_size": 100
  },
  "best_val_interpolation_mse": 0.11491959810256958,
  "test_metrics": {
    "loss": 0.27458467841148376,
    "observed_mse": 0.049962023347616194,
    "interpolation_mse": 0.10929998010396957,
    "extrapolation_mse": 0.48779685735702516,
    "nfe_per_sample": 0.0,
    "nfe_per_batch": 0.0
  },
  "history": [
    {
      "epoch": 1,
      "train_loss": 0.4234972493648529,
      "train_observed_mse": 0.4234972493648529,
      "train_interpolation_mse": 0.47823386430740356,
      "train_extrapolation_mse": null,
      "train_forward_nfe_per_sample": 0.0,
      "train_peak_memory_mb": 28.60302734375,
      "val_loss": 0.43631004929542544,
      "val_observed_mse": 0.34837024569511416,
      "val_interpolation_mse": 0.4336696743965149,
      "val_extrapolation_mse": 0.50784273147583,
      "val_forward_nfe_per_sample": 0.0,
      "best_val_interpolation_mse": 0.4336696743965149,
      "train_forward_nfe_per_batch": 0.0,
      "val_forward_nfe_per_batch": 0.0
    },
    {
      "epoch": 2,
      "train_loss": 0.2971458084583282,
      "train_observed_mse": 0.2971458084583282,
      "train_interpolation_mse": 0.3870760929584503,
      "train_extrapolation_mse": null,
      "train_forward_nfe_per_sample": 0.0,
      "train_peak_memory_mb": 28.6025390625,
      "val_loss": 0.37587939739227294,
      "val_observed_mse": 0.22911671221256255,
      "val_interpolation_mse": 0.34677119851112365,
      "val_extrapolation_mse": 0.49997576475143435,
      "val_forward_nfe_per_sample": 0.0,
      "best_val_interpolation_mse": 0.34677119851112365,
      "train_forward_nfe_per_batch": 0.0,
      "val_forward_nfe_per_batch": 0.0
    },
    {
      "epoch": 3,
      "train_loss": 0.16862388563156128,
      "train_observed_mse": 0.16862388563156128,
      "train_interpolation_mse": 0.28417647755146025,
      "train_extrapolation_mse": null,
      "train_forward_nfe_per_sample": 0.0,
      "train_peak_memory_mb": 28.60302734375,
      "val_loss": 0.3094001948833466,
      "val_observed_mse": 0.09292830973863601,
      "val_interpolation_mse": 0.22316791713237763,
      "val_extrapolation_mse": 0.5007324993610383,
      "val_forward_nfe_per_sample": 0.0,
      "best_val_interpolation_mse": 0.22316791713237763,
      "train_forward_nfe_per_batch": 0.0,
      "val_forward_nfe_per_batch": 0.0
    },
    {
      "epoch": 4,
      "train_loss": 0.060771015107631686,
      "train_observed_mse": 0.060771015107631686,
      "train_interpolation_mse": 0.16168638962507248,
      "train_extrapolation_mse": null,
      "train_forward_nfe_per_sample": 0.0,
      "train_peak_memory_mb": 28.60302734375,
      "val_loss": 0.28091263890266416,
      "val_observed_mse": 0.051371486485004426,
      "val_interpolation_mse": 0.11491959810256958,
      "val_extrapolation_mse": 0.4981382930278778,
      "val_forward_nfe_per_sample": 0.0,
      "best_val_interpolation_mse": 0.11491959810256958,
      "train_forward_nfe_per_batch": 0.0,
      "val_forward_nfe_per_batch": 0.0
    },
    {
      "epoch": 5,
      "train_loss": 0.049767915070056915,
      "train_observed_mse": 0.049767915070056915,
      "train_interpolation_mse": 0.10239563274383545,
      "train_extrapolation_mse": null,
      "train_forward_nfe_per_sample": 0.0,
      "train_peak_memory_mb": 28.60302734375,
      "val_loss": 0.27760802865028383,
      "val_observed_mse": 0.03792153909802437,
      "val_interpolation_mse": 0.11699121534824371,
      "val_extrapolation_mse": 0.5019641172885895,
      "val_forward_nfe_per_sample": 0.0,
      "best_val_interpolation_mse": 0.11491959810256958,
      "train_forward_nfe_per_batch": 0.0,
      "val_forward_nfe_per_batch": 0.0
    },
    {
      "epoch": 6,
      "train_loss": 0.03044894641637802,
      "train_observed_mse": 0.03044894641637802,
      "train_interpolation_mse": 0.12570093601942062,
      "train_extrapolation_mse": null,
      "train_forward_nfe_per_sample": 0.0,
      "train_peak_memory_mb": 28.6025390625,
      "val_loss": 0.27584789633750917,
      "val_observed_mse": 0.02773658439517021,
      "val_interpolation_mse": 0.15432414829730987,
      "val_extrapolation_mse": 0.4994703257083893,
      "val_forward_nfe_per_sample": 0.0,
      "best_val_interpolation_mse": 0.11491959810256958,
      "train_forward_nfe_per_batch": 0.0,
      "val_forward_nfe_per_batch": 0.0
    },
    {
      "epoch": 7,
      "train_loss": 0.02604342645406723,
      "train_observed_mse": 0.02604342645406723,
      "train_interpolation_mse": 0.15749623215198516,
      "train_extrapolation_mse": null,
      "train_forward_nfe_per_sample": 0.0,
      "train_peak_memory_mb": 28.60302734375,
      "val_loss": 0.2760358452796936,
      "val_observed_mse": 0.02394509509205818,
      "val_interpolation_mse": 0.1651061826944351,
      "val_extrapolation_mse": 0.5008181488513946,
      "val_forward_nfe_per_sample": 0.0,
      "best_val_interpolation_mse": 0.11491959810256958,
      "train_forward_nfe_per_batch": 0.0,
      "val_forward_nfe_per_batch": 0.0
    },
    {
      "epoch": 8,
      "train_loss": 0.021403257459402084,
      "train_observed_mse": 0.021403257459402084,
      "train_interpolation_mse": 0.15578105294704436,
      "train_extrapolation_mse": null,
      "train_forward_nfe_per_sample": 0.0,
      "train_peak_memory_mb": 28.60302734375,
      "val_loss": 0.2732624137401581,
      "val_observed_mse": 0.019865824207663536,
      "val_interpolation_mse": 0.1551777583360672,
      "val_extrapolation_mse": 0.500464322566986,
      "val_forward_nfe_per_sample": 0.0,
      "best_val_interpolation_mse": 0.11491959810256958,
      "train_forward_nfe_per_batch": 0.0,
      "val_forward_nfe_per_batch": 0.0
    },
    {
      "epoch": 9,
      "train_loss": 0.018620148867368697,
      "train_observed_mse": 0.018620148867368697,
      "train_interpolation_mse": 0.15177155017852784,
      "train_extrapolation_mse": null,
      "train_forward_nfe_per_sample": 0.0,
      "train_peak_memory_mb": 28.60302734375,
      "val_loss": 0.2726749300956726,
      "val_observed_mse": 0.01806090049445629,
      "val_interpolation_mse": 0.15791676104068755,
      "val_extrapolation_mse": 0.5002101480960846,
      "val_forward_nfe_per_sample": 0.0,
      "best_val_interpolation_mse": 0.11491959810256958,
      "train_forward_nfe_per_batch": 0.0,
      "val_forward_nfe_per_batch": 0.0
    },
    {
      "epoch": 10,
      "train_loss": 0.0167055938243866,
      "train_observed_mse": 0.0167055938243866,
      "train_interpolation_mse": 0.1620402374267578,
      "train_extrapolation_mse": null,
      "train_forward_nfe_per_sample": 0.0,
      "train_peak_memory_mb": 28.6025390625,
      "val_loss": 0.2733380925655365,
      "val_observed_mse": 0.015996318086981775,
      "val_interpolation_mse": 0.17455359518527985,
      "val_extrapolation_mse": 0.4999948501586914,
      "val_forward_nfe_per_sample": 0.0,
      "best_val_interpolation_mse": 0.11491959810256958,
      "train_forward_nfe_per_batch": 0.0,
      "val_forward_nfe_per_batch": 0.0
    }
  ]
}